poozzzith/__init__.py
poozzzith-0.1.3.dist-info/METADATA
poozzzith-0.1.3.dist-info/WHEEL
poozzzith-0.1.3.dist-info/entry_points.txt
poozzzith-0.1.3.dist-info/RECORD
