Metadata-Version: 2.1
Name: poozzzith
Version: 0.1.3
Summary: 
Author: SadineniAbhi
Author-email: abhisadineni@gmail.com
Requires-Python: >=3.7,<4.0
Classifier: Programming Language :: Python :: 3
Classifier: Programming Language :: Python :: 3.7
Classifier: Programming Language :: Python :: 3.8
Classifier: Programming Language :: Python :: 3.9
Classifier: Programming Language :: Python :: 3.10
Classifier: Programming Language :: Python :: 3.11
Classifier: Programming Language :: Python :: 3.12
Requires-Dist: pyfiglet (>=1.0.2,<2.0.0)
